h2ospawner/__init__.py
h2ospawner/h2ospawner.py
jupyterhub_h2ospawner-0.1.dist-info/LICENSE
jupyterhub_h2ospawner-0.1.dist-info/METADATA
jupyterhub_h2ospawner-0.1.dist-info/WHEEL
jupyterhub_h2ospawner-0.1.dist-info/top_level.txt
jupyterhub_h2ospawner-0.1.dist-info/RECORD
